examples/__init__.py
examples/introduction.ipynb
examples/.ipynb_checkpoints/__init__-checkpoint.py
examples/.ipynb_checkpoints/introduction-checkpoint.ipynb
examples/aa/Indresh/conditional/.01 - Around the lake.ipynb.sage-jupyter
examples/aa/Indresh/conditional/.02 - Its Going To Rain.ipynb.sage-jupyter
examples/aa/Indresh/conditional/.03 - A piece of cake!.ipynb.sage-jupyter
examples/aa/Indresh/conditional/.04 - I know how to count!.ipynb.sage-jupyter
examples/aa/Indresh/conditional/.05 - Fruit picking.ipynb.sage-jupyter
examples/aa/Indresh/conditional/001 - Hello.ipynb
examples/aa/Indresh/conditional/002 - Multiple.ipynb
examples/aa/Indresh/conditional/003 - Wall Street.ipynb
examples/aa/Indresh/conditional/01 - Around the lake.ipynb
examples/aa/Indresh/conditional/02 - Its Going To Rain.ipynb
examples/aa/Indresh/conditional/03 - A piece of cake!.ipynb
examples/aa/Indresh/conditional/04 - I know how to count!.ipynb
examples/aa/Indresh/conditional/05 - Fruit picking.ipynb
examples/aa/Indresh/conditional/.ipynb_checkpoints/01 - Around the lake-checkpoint.ipynb
examples/aa/Indresh/conditional/.ipynb_checkpoints/01 - IF I Can-checkpoint.ipynb
examples/aa/Indresh/conditional/.ipynb_checkpoints/02 - Its Going To Rain-checkpoint.ipynb
examples/aa/Indresh/conditional/.ipynb_checkpoints/03 - A piece of cake!-checkpoint.ipynb
examples/aa/Indresh/conditional/.ipynb_checkpoints/04 - I know how to count!-checkpoint.ipynb
examples/aa/Indresh/conditional/.ipynb_checkpoints/05 - Fruit picking-checkpoint.ipynb
examples/aa/Indresh/conditional/worlds/eight.json
examples/aa/Indresh/conditional/worlds/eight.py
examples/aa/Indresh/conditional/worlds/five.json
examples/aa/Indresh/conditional/worlds/five.py
examples/aa/Indresh/conditional/worlds/four.json
examples/aa/Indresh/conditional/worlds/four.py
examples/aa/Indresh/conditional/worlds/one.json
examples/aa/Indresh/conditional/worlds/one.py
examples/aa/Indresh/conditional/worlds/seven.json
ttgtcanvas2-0.1.41.dist-info/LICENSE.txt
ttgtcanvas2-0.1.41.dist-info/METADATA
ttgtcanvas2-0.1.41.dist-info/WHEEL
ttgtcanvas2-0.1.41.dist-info/top_level.txt
ttgtcanvas2-0.1.41.dist-info/RECORD
